ncrar_dkm_tools/__init__.py
ncrar_dkm_tools/event_filter.py
ncrar_dkm_tools/list_table.py
ncrar_dkm_tools/main.py
ncrar_dkm_tools/main_window.enaml
ncrar_dkm_tools/util.py
ncrar_dkm_tools/version.py
ncrar_dkm_tools-0.0.2.dist-info/METADATA
ncrar_dkm_tools-0.0.2.dist-info/WHEEL
ncrar_dkm_tools-0.0.2.dist-info/entry_points.txt
ncrar_dkm_tools-0.0.2.dist-info/top_level.txt
ncrar_dkm_tools-0.0.2.dist-info/RECORD
