Metadata-Version: 2.1
Name: ncrar-dkm-tools
Version: 0.0.2
Summary: Custom code for analyses done by DKM
Author-email: Brad Buran <bradley.buran@va.gov>
Maintainer-email: Brad Buran <bradley.buran@va.gov>
Requires-Python: >=3.10
Requires-Dist: enaml[qt6-pyside] (>=0.16.1)
Requires-Dist: pandas
Requires-Dist: xlsxwriter
